MANIFEST.in
README.txt
setup.py
cloudinitd/__init__.py
cloudinitd/bootfabtasks.py
cloudinitd/cb_iaas.py
cloudinitd/exceptions.py
cloudinitd/global_deps.py
cloudinitd/persistence.py
cloudinitd/pollables.py
cloudinitd/services.py
cloudinitd/statics.py
cloudinitd/user_api.py
cloudinitd.egg-info/PKG-INFO
cloudinitd.egg-info/SOURCES.txt
cloudinitd.egg-info/dependency_links.txt
cloudinitd.egg-info/entry_points.txt
cloudinitd.egg-info/requires.txt
cloudinitd.egg-info/top_level.txt
cloudinitd/cli/__init__.py
cloudinitd/cli/boot.py
cloudinitd/cli/cmd_opts.py
cloudinitd/cli/output.py
cloudinitd/nosetests/__init__.py
cloudinitd/nosetests/badplan_cleanup_tests.py
cloudinitd/nosetests/basic_tests.py
cloudinitd/nosetests/basic_unit_tests.py
cloudinitd/nosetests/cloudinitd_tests.py
cloudinitd/nosetests/instance_dies_tests.py
cloudinitd/nosetests/leak_vm_tests.py
cloudinitd/nosetests/localhost_tests.py
cloudinitd/nosetests/many_at_once_tests.py
cloudinitd/nosetests/many_terminate_hang_tests.py
cloudinitd/nosetests/outputjson_tests.py
cloudinitd/nosetests/plan_tests.py
cloudinitd/nosetests/pollable_tests.py
cloudinitd/nosetests/prelaunch_tests.py
cloudinitd/nosetests/remote_locations_tests.py
cloudinitd/nosetests/service_tests.py
cloudinitd/nosetests/service_unit_tests.py
cloudinitd/nosetests/singlevm_tests.py
cloudinitd/nosetests/tenservice_tests.py
cloudinitd/nosetests/validate_tests.py
tests/fakefab.sh
tests/run-tests.sh
tests/plans/back2backterminatehang/deps1.conf
tests/plans/back2backterminatehang/deps2_1.conf
tests/plans/back2backterminatehang/deps2_2.conf
tests/plans/back2backterminatehang/sampletest1.py
tests/plans/back2backterminatehang/test-level1.conf
tests/plans/back2backterminatehang/test-level2.conf
tests/plans/back2backterminatehang/top.conf
tests/plans/back2backterminatehang/webserver.json
tests/plans/back2backterminatehang/webserver.py
tests/plans/back2backterminatehang/webserver_dep.json
tests/plans/back2backterminatehang/webserver_dep_test.py
tests/plans/baddeps/deps1.conf
tests/plans/baddeps/deps2.conf
tests/plans/baddeps/sampletest1.py
tests/plans/baddeps/test-level1.conf
tests/plans/baddeps/test-level2.conf
tests/plans/baddeps/top.conf
