Metadata-Version: 1.0
Name: cloudinitd
Version: 1.3
Summary: An Open Source bootstrap tool for services in the cloud.
Home-page: http://www.nimbusproject.org/
Author: Nimbus Development Team
Author-email: nimbus@mcs.anl.gov
License: Apache2
Download-URL: http://www.nimbusproject.org/downloads/cloudinitd-1.3.tar.gz
Keywords: cloud boot tool initialize services
Platform: UNKNOWN
Classifier: Development Status :: 4 - Beta
Classifier: Environment :: Console
Classifier: Intended Audience :: End Users/Desktop
Classifier: Intended Audience :: Developers
Classifier: Intended Audience :: System Administrators
Classifier: License :: OSI Approved :: Apache Software License
Classifier: Operating System :: MacOS :: MacOS X
Classifier: Operating System :: Microsoft :: Windows
Classifier: Operating System :: POSIX
Classifier: Operating System :: POSIX :: Linux
Classifier: Programming Language :: Python
Classifier: Topic :: System :: Clustering
Classifier: Topic :: System :: Distributed Computing
